{"session_file": "+224627403828", "phone": "+224627403828", "register_time": 1671744077, "app_id": 1, "app_hash": "b6b154c3707471f5339bd661645ed3d6", "sdk": "Android 7.1.2 Nougat MIUI 10", "app_version": "9.76.33", "device": "Archos40bTitanium", "last_check_time": 1671744077, "avatar": "null", "first_name": "Cassandra", "last_name": "Escobar", "username": "robinsonalexandra447", "sex": 0, "lang_pack": "nl", "system_lang_pack": "am", "proxy": [3, "2.56.119.73", 5054, true, "tgkopadmin", "privatechannel"], "ipv6": false, "twoFA": "null", "chimera_status": "valid"}